setup.py
tester_coverage/__init__.py
tester_coverage.egg-info/PKG-INFO
tester_coverage.egg-info/SOURCES.txt
tester_coverage.egg-info/dependency_links.txt
tester_coverage.egg-info/top_level.txt