Metadata-Version: 1.1
Name: tester-coverage
Version: 1.0
Summary: Class for autotests with incremental coverage call for python apps
Home-page: https://github.com/vb64/test.helper.coverage
Author: Vitaly Bogomolov
Author-email: mail@vitaly-bogomolov.ru
License: UNKNOWN
Download-URL: https://github.com/vb64/test.helper.coverage/archive/v1.0.tar.gz
Keywords: python,Python27,coverage,unittest
Platform: UNKNOWN
Classifier: Programming Language :: Python :: 2.7
Classifier: License :: OSI Approved :: MIT License
Classifier: Operating System :: OS Independent
